{
  "schema": "SPIRA_NESIRA_PHASE1_EXTERNAL_REPRODUCTION_AUTHORIZATION_REVIEW_RESULTS_V1",
  "schema_version": "1.0",
  "verdict": "SPIRA_NESIRA_PHASE1_EXTERNAL_REPRODUCTION_AUTHORIZATION_ACCEPTED",
  "accepted_phase1_implementation_commit": "a6e69cf8ea17a1a7d8e188cf3da6735cbfa7a0aa",
  "hygiene_clean_reproduction_source_commit": "c21abef47dd174284a5d1938182a633b93bd8785",
  "accepted_phase1_verdict": "SPIRA_NESIRA_PHASE1_VALIDATOR_ACCEPTED",
  "authorization_v1_1_sha256": "14b19bbce4764778599b755ce614404ecc6875349c63a08efa9ad5439ef5370d",
  "baseline_commit": "df2bd9db4e5d599a9e4a72dde2124a076e1e3dfe",
  "authorized_artifact_types": [
    "SEVERANCE_AUTHORIZATION",
    "LEGACY_ISOLATION_RESULT"
  ],
  "authorized_claim": "SPIRA validates structure, binding, evidence integrity, and safe evidence paths for the two supported Phase 1 artifact types.",
  "prohibited_claims": [
    "cryptographic signature verification",
    "signer identity",
    "signer authority",
    "signer trust",
    "actual isolation execution",
    "independent isolation observation",
    "severance authorization",
    "permission to sever",
    "production readiness",
    "product integration",
    "public capability availability",
    "Phase 1 validator is formally proved",
    "DSSE parser is formally proved",
    "path validation is formally proved",
    "end-to-end trust is formally proved"
  ],
  "fresh_clone_required_or_clean_worktree_allowed": true,
  "two_runs_required": true,
  "fixture_level_results_required": true,
  "mutation_pair_results_required": true,
  "path_security_matrix_required": true,
  "hash_binding_matrix_required": true,
  "protected_surface_check_required": true,
  "public_wheel_exclusion_required": true,
  "source_identity_required": true,
  "local_path_scan_required": true,
  "secret_scan_required": true,
  "deterministic_package_required": true,
  "cold_review_task_required": true,
  "v1_1_authorization_package_verification_required": true,
  "v1_1_authorization_package_not_available_status": "NOT_EVALUATED",
  "required_acceptance_metrics": {
    "positive_fixtures_structurally_accepted": "6/6",
    "positive_fixtures_yielding_PROCEED": "0/6",
    "negative_invariant_detection": "100%",
    "false_VALID_mutation_pairs": 0,
    "unsafe_evidence_paths_accepted": 0,
    "hash_mismatches_accepted": 0,
    "directories_accepted_as_evidence_files": 0,
    "duplicate_canonical_evidence_paths_accepted": 0,
    "local_absolute_paths_leaked_in_results": 0,
    "PROCEED_paths": 0,
    "stop_false_paths": 0
  },
  "required_command_classes": [
    "python -m compileall",
    "focused Phase 1 pytest",
    "all path-security tests",
    "all hash-binding tests",
    "all mutation tests",
    "full pytest",
    "public wheel build",
    "wheel archive inspection",
    "JSON validation",
    "protected-surface diff",
    "action/schema identity checks",
    "git diff --check"
  ],
  "phase2_authorized": false,
  "product_integration_authorized": false,
  "public_claim_authorized": false,
  "release_authorized": false,
  "reproduction_package_build_authorized_in_this_step": false,
  "external_reproduction_execution_authorized_in_this_step": false,
  "blockers": [],
  "next_step": "SPIRA_NESIRA_PHASE1_EXTERNAL_REPRODUCTION_PACKAGE_BUILD_REQUIRED"
}
